noteout/__init__.py
noteout/filter_divspans.py
noteout/nb_only.py
noteout/write_meta.py
noteout/write_notebooks.py
noteout/tests/__init__.py
noteout/tests/nb1.Rmd
noteout/tests/nb1_no_py.Rmd
noteout/tests/nb1_no_r.Rmd
noteout/tests/nb1_python_nbs.Rmd
noteout/tests/nb1_r_nbs.Rmd
noteout/tests/nb2.Rmd
noteout/tests/test_nb1.py
noteout/tests/test_nb2.py
noteout/tests/test_nb_only.py
noteout/tests/test_qbook.py
noteout/tests/tutils.py
noteout/tests/qbook/.gitignore
noteout/tests/qbook/Makefile
noteout/tests/qbook/_quarto.yml
noteout/tests/qbook/_variables.yml
noteout/tests/qbook/index.qmd
noteout/tests/qbook/intro.Rmd
noteout/tests/qbook/lough_erne.csv
noteout/tests/qbook/references.bib
noteout/tests/qbook/references.qmd
noteout/tests/qbook/summary.qmd
noteout-0.0.2.dist-info/entry_points.txt
noteout-0.0.2.dist-info/LICENSE
noteout-0.0.2.dist-info/WHEEL
noteout-0.0.2.dist-info/METADATA
noteout-0.0.2.dist-info/RECORD
