Metadata-Version: 2.1
Name: noteout
Version: 0.0.2
Summary: Notebook parsing filters for Pandoc
Home-page: https://github.com/matthew-brett/noteout
Author: Matthew Brett
Author-email: matthew.brett@gmail.com
Requires-Python: >=3.6
Classifier: License :: OSI Approved :: BSD License
Classifier: Programming Language :: Python :: 3
Requires-Dist: panflute
Requires-Dist: jupytext
